LICENSE
MANIFEST.in
README.rst
setup.py
idempotent_sequence.egg-info/PKG-INFO
idempotent_sequence.egg-info/SOURCES.txt
idempotent_sequence.egg-info/dependency_links.txt
idempotent_sequence.egg-info/entry_points.txt
idempotent_sequence.egg-info/requires.txt
idempotent_sequence.egg-info/top_level.txt
idemseq/__init__.py
idemseq/base.py
idemseq/cli.py
idemseq/command.py
idemseq/controller.py
idemseq/exceptions.py
idemseq/log.py
idemseq/persistence.py
idemseq/sequence.py
idemseq/examples/__init__.py
idemseq/examples/example01.py
idemseq/examples/example02.py