Metadata-Version: 1.1
Name: idempotent-sequence
Version: 3.0.0
Summary: Organise a set of units of code in a sequence that can be rerun repeatedly skipping already completed units
Home-page: https://github.com/jbasko/idempotent-sequence
Author: Jazeps Basko
Author-email: jazeps.basko@gmail.com
License: MIT
Platform: UNKNOWN
Classifier: Development Status :: 3 - Alpha
Classifier: Intended Audience :: Developers
Classifier: Programming Language :: Python
Classifier: Programming Language :: Python :: 3
Classifier: Programming Language :: Python :: 3.5
Classifier: License :: OSI Approved :: MIT License
